README.md
setup.py
omemo_backend_signal/__init__.py
omemo_backend_signal/backend.py
omemo_backend_signal/project.py
omemo_backend_signal/version.py
omemo_backend_signal/whispertextprotocol_pb2.py
omemo_backend_signal/wireformat.py
omemo_backend_signal.egg-info/PKG-INFO
omemo_backend_signal.egg-info/SOURCES.txt
omemo_backend_signal.egg-info/dependency_links.txt
omemo_backend_signal.egg-info/not-zip-safe
omemo_backend_signal.egg-info/requires.txt
omemo_backend_signal.egg-info/top_level.txt
omemo_backend_signal/doubleratchet/__init__.py
omemo_backend_signal/doubleratchet/cbcaead.py
omemo_backend_signal/doubleratchet/doubleratchet.py
omemo_backend_signal/doubleratchet/rootchain.py
omemo_backend_signal/doubleratchet/sendrecvchain.py
omemo_backend_signal/doubleratchet/symmetrickeyratchet.py
omemo_backend_signal/x3dh/__init__.py
omemo_backend_signal/x3dh/state.py
omemo_backend_signal/x3dh/x3dhpkencoder.py