Metadata-Version: 2.1
Name: omemo-backend-signal
Version: 0.3.1
Summary: A backend for python-omemo offering compatibility with libsignal.
Home-page: https://github.com/Syndace/python-omemo-backend-signal
Author: Tim Henkes (Syndace)
Author-email: me@syndace.dev
License: GPLv3
Platform: UNKNOWN
Classifier: Intended Audience :: Developers
Classifier: License :: OSI Approved :: MIT License
Classifier: Programming Language :: Python :: 3
Classifier: Programming Language :: Python :: 3 :: Only
Classifier: Programming Language :: Python :: 3.6
Classifier: Programming Language :: Python :: 3.7
Classifier: Programming Language :: Python :: 3.8
Classifier: Programming Language :: Python :: 3.9
Classifier: Programming Language :: Python :: 3.10
Classifier: Programming Language :: Python :: Implementation :: CPython
Classifier: Programming Language :: Python :: Implementation :: PyPy
Classifier: Topic :: Communications :: Chat
Classifier: Topic :: Security :: Cryptography
Classifier: Development Status :: 4 - Beta
Requires-Python: >=3.6,<4
